asyncpgdb/__init__.py
asyncpgdb/asyncpg.py
asyncpgdb/connection.py
asyncpgdb/database.py
asyncpgdb/dsn.py
asyncpgdb/exception.py
asyncpgdb/execute.py
asyncpgdb/pool.py
asyncpgdb/settings.py
asyncpgdb/sql.py
asyncpgdb/typing.py
asyncpgdb/util.py
asyncpgdb-0.0.23.dist-info/METADATA
asyncpgdb-0.0.23.dist-info/WHEEL
asyncpgdb-0.0.23.dist-info/RECORD
